bank_scrape/bca_credit.py
bank_scrape/bca_debit.py
bank_scrape/jenius_credit.py
bank_scrape/utils/common.py
rdxz2_bank_scrape-0.0.1.dist-info/licenses/LICENSE
rdxz2_bank_scrape-0.0.1.dist-info/METADATA
rdxz2_bank_scrape-0.0.1.dist-info/WHEEL
rdxz2_bank_scrape-0.0.1.dist-info/top_level.txt
rdxz2_bank_scrape-0.0.1.dist-info/RECORD
