Metadata-Version: 2.4
Name: rdxz2-bank-scrape
Version: 0.0.1
Summary: Just scraping bank transaction documents
Author-email: Richard Dharmawan <richard.dharmawan@gmail.com>
License: MIT License
Classifier: Programming Language :: Python :: 3
Classifier: Programming Language :: Python :: 3.12
Classifier: Programming Language :: Python :: 3 :: Only
Classifier: License :: OSI Approved :: MIT License
Classifier: Operating System :: OS Independent
Requires-Python: >=3.12
License-File: LICENSE
Requires-Dist: PyPDF2<4,>=3.0.1
Requires-Dist: pycryptodome<4,>=3
Requires-Dist: pydantic<3,>=2
Dynamic: license-file
